pyvolt/__init__.py
pyvolt/__main__.py
pyvolt/abc.py
pyvolt/adapter.py
pyvolt/authentication.py
pyvolt/base.py
pyvolt/bot.py
pyvolt/cache.py
pyvolt/cdn.py
pyvolt/channel.py
pyvolt/client.py
pyvolt/context_managers.py
pyvolt/core.py
pyvolt/discovery.py
pyvolt/embed.py
pyvolt/emoji.py
pyvolt/enums.py
pyvolt/errors.py
pyvolt/events.py
pyvolt/flags.py
pyvolt/http.py
pyvolt/instance.py
pyvolt/invite.py
pyvolt/message.py
pyvolt/parser.py
pyvolt/permissions.py
pyvolt/py.typed
pyvolt/read_state.py
pyvolt/routes.py
pyvolt/safety_reports.py
pyvolt/server.py
pyvolt/settings.py
pyvolt/shard.py
pyvolt/state.py
pyvolt/ulid.py
pyvolt/user.py
pyvolt/utils.py
pyvolt/webhook.py
pyvolt/ext/chunking/__init__.py
pyvolt/ext/chunking/member_chunker.py
pyvolt/ext/commands/__init__.py
pyvolt/ext/commands/_types.py
pyvolt/ext/commands/bot.py
pyvolt/ext/commands/cache.py
pyvolt/ext/commands/context.py
pyvolt/ext/commands/converter.py
pyvolt/ext/commands/cooldown.py
pyvolt/ext/commands/core.py
pyvolt/ext/commands/errors.py
pyvolt/ext/commands/events.py
pyvolt/ext/commands/gear.py
pyvolt/ext/commands/parameters.py
pyvolt/ext/commands/view.py
pyvolt/raw/__init__.py
pyvolt/raw/authifier.py
pyvolt/raw/basic.py
pyvolt/raw/bots.py
pyvolt/raw/channel_invites.py
pyvolt/raw/channel_unreads.py
pyvolt/raw/channel_webhooks.py
pyvolt/raw/channels.py
pyvolt/raw/discovery.py
pyvolt/raw/embeds.py
pyvolt/raw/emojis.py
pyvolt/raw/files.py
pyvolt/raw/gateway.py
pyvolt/raw/localization.py
pyvolt/raw/messages.py
pyvolt/raw/misc.py
pyvolt/raw/permissions.py
pyvolt/raw/safety_reports.py
pyvolt/raw/server_bans.py
pyvolt/raw/server_members.py
pyvolt/raw/servers.py
pyvolt/raw/user_settings.py
pyvolt/raw/users.py
pyvolt_re-1.1.0.dist-info/licenses/LICENSE
pyvolt_re-1.1.0.dist-info/METADATA
pyvolt_re-1.1.0.dist-info/WHEEL
pyvolt_re-1.1.0.dist-info/top_level.txt
pyvolt_re-1.1.0.dist-info/RECORD
