Metadata-Version: 2.4
Name: pyvolt-re
Version: 1.1.0
Summary: A Python wrapper for the Revolt API
Author: MCausc78
License: MIT License
Project-URL: Documentation, https://pyvolt.readthedocs.io/en/latest/
Project-URL: Issue tracker, https://github.com/MCausc78/pyvolt/issues
Classifier: Development Status :: 4 - Beta
Classifier: License :: OSI Approved :: MIT License
Classifier: Intended Audience :: Developers
Classifier: Natural Language :: English
Classifier: Operating System :: OS Independent
Classifier: Programming Language :: Python :: 3.10
Classifier: Programming Language :: Python :: 3.11
Classifier: Programming Language :: Python :: 3.12
Classifier: Topic :: Internet
Classifier: Topic :: Software Development :: Libraries
Classifier: Topic :: Software Development :: Libraries :: Python Modules
Classifier: Topic :: Utilities
Classifier: Typing :: Typed
Requires-Python: >=3.10
License-File: LICENSE
Requires-Dist: aiohttp<4,>=3.9.5
Requires-Dist: attrs>=24.2.0
Provides-Extra: voice
Requires-Dist: livekit>=0.18.1; extra == "voice"
Provides-Extra: speed
Requires-Dist: orjson>=3.5.4; extra == "speed"
Requires-Dist: aiodns>=1.1; extra == "speed"
Requires-Dist: Brotli; extra == "speed"
Provides-Extra: test
Requires-Dist: pytest; extra == "test"
Requires-Dist: pytest-asyncio; extra == "test"
Requires-Dist: typing-extensions<5,>=4.3; extra == "test"
Requires-Dist: tzdata; sys_platform == "win32" and extra == "test"
Provides-Extra: docs
Requires-Dist: Sphinx<9,>=8.1.3; extra == "docs"
Requires-Dist: sphinxcontrib_trio==1.1.2; extra == "docs"
Requires-Dist: sphinxcontrib-websupport<3,>=2.0.0; extra == "docs"
Requires-Dist: sphinxcontrib-devhelp<3,>=2.0.0; extra == "docs"
Requires-Dist: sphinxcontrib-htmlhelp<3,>=2.1.0; extra == "docs"
Requires-Dist: sphinxcontrib-jsmath<2,>=1.0.1; extra == "docs"
Requires-Dist: sphinxcontrib-qthelp<3,>=2.0.0; extra == "docs"
Requires-Dist: sphinxcontrib-serializinghtml<3,>=2.0.0; extra == "docs"
Requires-Dist: typing-extensions<5,>=4.3; extra == "docs"
Requires-Dist: sphinx-inline-tabs==2023.4.21; extra == "docs"
Requires-Dist: furo==2024.8.6; extra == "docs"
Dynamic: license-file
